MANIFEST.in
setup.py
docs/HISTORY.txt
src/dolmen/__init__.py
src/dolmen.forms.wizard.egg-info/PKG-INFO
src/dolmen.forms.wizard.egg-info/SOURCES.txt
src/dolmen.forms.wizard.egg-info/dependency_links.txt
src/dolmen.forms.wizard.egg-info/namespace_packages.txt
src/dolmen.forms.wizard.egg-info/not-zip-safe
src/dolmen.forms.wizard.egg-info/requires.txt
src/dolmen.forms.wizard.egg-info/top_level.txt
src/dolmen/forms/__init__.py
src/dolmen/forms/wizard/README.txt
src/dolmen/forms/wizard/__init__.py
src/dolmen/forms/wizard/actions.py
src/dolmen/forms/wizard/interfaces.py
src/dolmen/forms/wizard/meta.py
src/dolmen/forms/wizard/wizard.py
src/dolmen/forms/wizard/default_templates/steptemplate.pt
src/dolmen/forms/wizard/default_templates/wizardtemplate.pt
src/dolmen/forms/wizard/locales/de/LC_MESSAGES/dolmen.forms.wizard.mo
src/dolmen/forms/wizard/locales/de/LC_MESSAGES/dolmen.forms.wizard.po
src/dolmen/forms/wizard/locales/en/LC_MESSAGES/dolmen.forms.wizard.po
src/dolmen/forms/wizard/tests/__init__.py
src/dolmen/forms/wizard/tests/rendering.py
src/dolmen/forms/wizard/tests/steps.py
src/dolmen/forms/wizard/tests/test_browser.py
src/dolmen/forms/wizard/tests/wizard.txt